LICENSE
MANIFEST.in
README.rst
setup.cfg
setup.py
serialstruct/__init__.py
serialstruct.egg-info/PKG-INFO
serialstruct.egg-info/SOURCES.txt
serialstruct.egg-info/dependency_links.txt
serialstruct.egg-info/requires.txt
serialstruct.egg-info/top_level.txt
test/test_serialstruct.py