Metadata-Version: 1.0
Name: serialstruct
Version: 1.0.23
Summary: Implements a StructuredPacket for pySerial's serial.threaded module
Home-page: https://github.com/eoswald/serialstruct
Author: Eric Oswald
Author-email: eoswald39@gmail.com
License: MIT
Platform: UNKNOWN
